xtls_client/__init__.py
xtls_client/__version__.py
xtls_client/cffi.py
xtls_client/cookies.py
xtls_client/exceptions.py
xtls_client/fingerprint_loader.py
xtls_client/response.py
xtls_client/sessions.py
xtls_client/settings.py
xtls_client/structures.py
xtls_client/update_shared_libraries.py
xtls_client/utils.py
xtls_client/async_client/__init__.py
xtls_client/async_client/sessions.py
xtls_client/dependencies/__init__.py
xtls_client/dependencies/tls-client-32.dll
xtls_client/dependencies/tls-client-64.dll
xtls_client/dependencies/tls-client-amd64.so
xtls_client/dependencies/tls-client-arm64.dylib
xtls_client/dependencies/tls-client-arm64.so
xtls_client/dependencies/tls-client-x86.dylib
xtls_client/dependencies/tls-client-x86.so
xtls_client/dependencies/__pycache__/__init__.cpython-311.pyc
xtls_client-0.0.13.data/data/tls_datas/chrome/macos/chrome_132_macos_10_15_7_wechat.json
xtls_client-0.0.13.data/data/tls_datas/chrome/macos/chrome_139_macos_10_15_7.json
xtls_client-0.0.13.data/data/tls_datas/chrome/macos/chrome_139_macos_10_15_7_variant.json
xtls_client-0.0.13.data/data/tls_datas/chrome/macos/chrome_139_macos_10_15_7_variant_51313263.json
xtls_client-0.0.13.data/data/tls_datas/chrome/macos/chrome_139_macos_10_15_7_variant_cd419845.json
xtls_client-0.0.13.data/data/tls_datas/chrome/macos/chrome_141_macos_10_15_7.json
xtls_client-0.0.13.data/data/tls_datas/chrome/macos/chrome_141_macos_10_15_7_variant_47bb0881.json
xtls_client-0.0.13.data/data/tls_datas/chrome/macos/chrome_141_macos_10_15_7_variant_4f8e1578.json
xtls_client-0.0.13.data/data/tls_datas/chrome/macos/chrome_141_macos_10_15_7_variant_6d03bf5a.json
xtls_client-0.0.13.data/data/tls_datas/chrome/macos/chrome_141_macos_10_15_7_variant_b9ce185e.json
xtls_client-0.0.13.data/data/tls_datas/chrome/macos/chrome_141_macos_10_15_7_variant_peetws.json
xtls_client-0.0.13.data/data/tls_datas/chrome/macos/edge_139_macos_10_15_7.json
xtls_client-0.0.13.data/data/tls_datas/chrome/windows/chrome_109_windows_10_wow64.json
xtls_client-0.0.13.dist-info/licenses/LICENSE
xtls_client-0.0.13.dist-info/METADATA
xtls_client-0.0.13.dist-info/WHEEL
xtls_client-0.0.13.dist-info/top_level.txt
xtls_client-0.0.13.dist-info/RECORD
